MANIFEST.in
README.md
setup.py
pyMarkupL/__init__.py
pyMarkupL/__main__.py
pyMarkupL/help.txt
pyMarkupL.egg-info/PKG-INFO
pyMarkupL.egg-info/SOURCES.txt
pyMarkupL.egg-info/dependency_links.txt
pyMarkupL.egg-info/entry_points.txt
pyMarkupL.egg-info/top_level.txt
pyMarkupL/core/__init__.py
pyMarkupL/core/command.py
pyMarkupL/core/compiler.py
pyMarkupL/core/elements.py
pyMarkupL/core/exceptions.py
pyMarkupL/core/mamber_manager.py
pyMarkupL/core/management.py
pyMarkupL/core/decorators/__init__.py
pyMarkupL/core/decorators/command_decoratos.py
pyMarkupL/management/__init__.py
pyMarkupL/management/pml.py
pyMarkupL/startstructure/manage.py
pyMarkupL/startstructure/settings.py
pyMarkupL/startstructure/src/main.py
pyMarkupL/startstructure/src/components/box.py
pyMarkupL/startstructure/src/components/text.py
pyMarkupL/startstructure/src/components/toolbar.py
pyMarkupL/startstructure/src/components/static/style.py