Metadata-Version: 2.1
Name: pyMarkupL
Version: 1.0.0b2
Summary: Streamline the production of your HTML page using this python framework.
Home-page: https://github.com/Sandro-Meireles/pyMarkupL
Author: Sandro Meireles
Author-email: sandro.meirelesdev@gmail.com
License: MIT
Project-URL: Source, https://github.com/Sandro-Meireles/pyMarkupL
Keywords: pymarkupl html react css javascript
Platform: UNKNOWN
Classifier: Programming Language :: Python :: 3.6
Classifier: Development Status :: 4 - Beta
Classifier: License :: OSI Approved :: MIT License
